Workbook

Sheet Portfolio Summary
A1: Pomona Drinks Inventory Availability Improvement Project | B1: Pomona Drinks Inventory Availability Improvement Project | C1: Pomona Drinks Inventory Availability Improvement Project | D1: Pomona Drinks Inventory Availability Improvement Project | E1: Pomona Drinks Inventory Availability Improvement Project | F1: Pomona Drinks Inventory Availability Improvement Project | G1: Pomona Drinks Inventory Availability Improvement Project | H1: Pomona Drinks Inventory Availability Improvement Project
A2: Pomona Drinks Inventory Availability Improvement Project | B2: Pomona Drinks Inventory Availability Improvement Project | C2: Pomona Drinks Inventory Availability Improvement Project | D2: Pomona Drinks Inventory Availability Improvement Project | E2: Pomona Drinks Inventory Availability Improvement Project | F2: Pomona Drinks Inventory Availability Improvement Project | G2: Pomona Drinks Inventory Availability Improvement Project | H2: Pomona Drinks Inventory Availability Improvement Project
A4: Project Manager | B4: Agnes Iwaye | D4: PROJECT MANAGEMENT APPROACH | E4: PROJECT MANAGEMENT APPROACH | F4: PROJECT MANAGEMENT APPROACH | G4: PROJECT MANAGEMENT APPROACH | H4: PROJECT MANAGEMENT APPROACH
A5: Client | B5: Pomona Drinks (illustrative) | D5: 1. Diagnose — Reviewed monthly orders, receipts, shipments and peak-period patterns.
A6: Operation | B6: Inbound receipt, two-pack kitting, warehousing, outbound fulfillment and last-mile delivery | D6: 2. Define — Established minimum stock, safety stock and reorder points by SKU.
A7: Business problem | B7: Peak-season demand repeatedly depleted warehouse inventory, interrupting packing and deliveries to retail stores. | D7: 3. Build — Created a live inventory tracker with red/amber/green conditional alerts.
A8: Goal | B8: Prevent stockouts while supporting higher festive-period delivery volume. | D8: 4. Implement — Aligned warehouse and client replenishment decisions to alert thresholds.
A9: Solution | B9: Built SKU-level monthly benchmarks, reorder points, weeks-of-cover measures and conditional alerts using historical demand patterns. | D9: 5. Monitor — Tracked fill rate, stockouts, weeks of cover, forecast accuracy and delivery volume.
A10: Outcome | B10: Illustrative model shows zero stockout events in the post-implementation period and delivery volume approximately doubling during the peak comparison window. | D10: 6. Improve — Adjusted peak multipliers and benchmarks based on actual consumption.

Sheet Dashboard
A1: Supply Chain Performance Dashboard | B1: Supply Chain Performance Dashboard | C1: Supply Chain Performance Dashboard | D1: Supply Chain Performance Dashboard | E1: Supply Chain Performance Dashboard | F1: Supply Chain Performance Dashboard | G1: Supply Chain Performance Dashboard | H1: Supply Chain Performance Dashboard | I1: Supply Chain Performance Dashboard | J1: Supply Chain Performance Dashboard | K1: Supply Chain Performance Dashboard | L1: Supply Chain Performance Dashboard
A2: Supply Chain Performance Dashboard | B2: Supply Chain Performance Dashboard | C2: Supply Chain Performance Dashboard | D2: Supply Chain Performance Dashboard | E2: Supply Chain Performance Dashboard | F2: Supply Chain Performance Dashboard | G2: Supply Chain Performance Dashboard | H2: Supply Chain Performance Dashboard | I2: Supply Chain Performance Dashboard | J2: Supply Chain Performance Dashboard | K2: Supply Chain Performance Dashboard | L2: Supply Chain Performance Dashboard
A3: Baseline: Jan–Jun 2025 | Improved process: Jul–Dec 2025 | Synthetic portfolio data | B3: Baseline: Jan–Jun 2025 | Improved process: Jul–Dec 2025 | Synthetic portfolio data | C3: Baseline: Jan–Jun 2025 | Improved process: Jul–Dec 2025 | Synthetic portfolio data | D3: Baseline: Jan–Jun 2025 | Improved process: Jul–Dec 2025 | Synthetic portfolio data | E3: Baseline: Jan–Jun 2025 | Improved process: Jul–Dec 2025 | Synthetic portfolio data | F3: Baseline: Jan–Jun 2025 | Improved process: Jul–Dec 2025 | Synthetic portfolio data | G3: Baseline: Jan–Jun 2025 | Improved process: Jul–Dec 2025 | Synthetic portfolio data | H3: Baseline: Jan–Jun 2025 | Improved process: Jul–Dec 2025 | Synthetic portfolio data | I3: Baseline: Jan–Jun 2025 | Improved process: Jul–Dec 2025 | Synthetic portfolio data | J3: Baseline: Jan–Jun 2025 | Improved process: Jul–Dec 2025 | Synthetic portfolio data | K3: Baseline: Jan–Jun 2025 | Improved process: Jul–Dec 2025 | Synthetic portfolio data | L3: Baseline: Jan–Jun 2025 | Improved process: Jul–Dec 2025 | Synthetic portfolio data
A5: POST-PROCESS FILL RATE | D5: STOCKOUT UNITS | G5: ON-TIME DELIVERY RATE | J5: PEAK VOLUME GROWTH
A6: =SUMIFS('Historical Data'!$G$4:$G$75,'Historical Data'!$A$4:$A$75,">="&DATE(2025,7,1))/SUMIFS('Historical Data'!$F$4:$F$75,'Historical Data'!$A$4:$A$75,">="&DATE(2025,7,1)) -> 1 | D6: =SUMIFS('Historical Data'!$I$4:$I$75,'Historical Data'!$A$4:$A$75,">="&DATE(2025,7,1)) -> 0 | G6: =SUMIFS('Historical Data'!$M$4:$M$75,'Historical Data'!$A$4:$A$75,">="&DATE(2025,7,1))/SUMIFS('Historical Data'!$K$4:$K$75,'Historical Data'!$A$4:$A$75,">="&DATE(2025,7,1)) -> 0.97977941 | J6: =SUMIFS('Historical Data'!$G$4:$G$75,'Historical Data'!$A$4:$A$75,">="&DATE(2025,11,1))/SUMIFS('Historical Data'!$G$4:$G$75,'Historical Data'!$A$4:$A$75,">="&DATE(2025,5,1),'Historical Data'!$A$4:$A$75,"<"&DATE(2025,7,1))-1 -> 0.95925387
A10: Month | B10: Demand | C10: Shipped | D10: Fill Rate | E10: Stockout Units
A11: Jan | B11: =SUMIFS('Historical Data'!$F$4:$F$75,'Historical Data'!$A$4:$A$75,DATE(2025,1,1)) -> 4180 | C11: =SUMIFS('Historical Data'!$G$4:$G$75,'Historical Data'!$A$4:$A$75,DATE(2025,1,1)) -> 3761 | D11: =IFERROR(C11/B11,0) -> 0.89976077 | E11: =SUMIFS('Historical Data'!$I$4:$I$75,'Historical Data'!$A$4:$A$75,DATE(2025,1,1)) -> 419
A12: Feb | B12: =SUMIFS('Historical Data'!$F$4:$F$75,'Historical Data'!$A$4:$A$75,DATE(2025,2,1)) -> 4215 | C12: =SUMIFS('Historical Data'!$G$4:$G$75,'Historical Data'!$A$4:$A$75,DATE(2025,2,1)) -> 3794 | D12: =IFERROR(C12/B12,0) -> 0.90011862 | E12: =SUMIFS('Historical Data'!$I$4:$I$75,'Historical Data'!$A$4:$A$75,DATE(2025,2,1)) -> 421
A13: Mar | B13: =SUMIFS('Historical Data'!$F$4:$F$75,'Historical Data'!$A$4:$A$75,DATE(2025,3,1)) -> 4220 | C13: =SUMIFS('Historical Data'!$G$4:$G$75,'Historical Data'!$A$4:$A$75,DATE(2025,3,1)) -> 3799 | D13: =IFERROR(C13/B13,0) -> 0.90023697 | E13: =SUMIFS('Historical Data'!$I$4:$I$75,'Historical Data'!$A$4:$A$75,DATE(2025,3,1)) -> 421
A14: Apr | B14: =SUMIFS('Historical Data'!$F$4:$F$75,'Historical Data'!$A$4:$A$75,DATE(2025,4,1)) -> 4188 | C14: =SUMIFS('Historical Data'!$G$4:$G$75,'Historical Data'!$A$4:$A$75,DATE(2025,4,1)) -> 3768 | D14: =IFERROR(C14/B14,0) -> 0.89971347 | E14: =SUMIFS('Historical Data'!$I$4:$I$75,'Historical Data'!$A$4:$A$75,DATE(2025,4,1)) -> 420
A15: May | B15: =SUMIFS('Historical Data'!$F$4:$F$75,'Historical Data'!$A$4:$A$75,DATE(2025,5,1)) -> 4169 | C15: =SUMIFS('Historical Data'!$G$4:$G$75,'Historical Data'!$A$4:$A$75,DATE(2025,5,1)) -> 3753 | D15: =IFERROR(C15/B15,0) -> 0.90021588 | E15: =SUMIFS('Historical Data'!$I$4:$I$75,'Historical Data'!$A$4:$A$75,DATE(2025,5,1)) -> 416
A16: Jun | B16: =SUMIFS('Historical Data'!$F$4:$F$75,'Historical Data'!$A$4:$A$75,DATE(2025,6,1)) -> 4229 | C16: =SUMIFS('Historical Data'!$G$4:$G$75,'Historical Data'!$A$4:$A$75,DATE(2025,6,1)) -> 3806 | D16: =IFERROR(C16/B16,0) -> 0.89997635 | E16: =SUMIFS('Historical Data'!$I$4:$I$75,'Historical Data'!$A$4:$A$75,DATE(2025,6,1)) -> 423
A17: Jul | B17: =SUMIFS('Historical Data'!$F$4:$F$75,'Historical Data'!$A$4:$A$75,DATE(2025,7,1)) -> 5265 | C17: =SUMIFS('Historical Data'!$G$4:$G$75,'Historical Data'!$A$4:$A$75,DATE(2025,7,1)) -> 5265 | D17: =IFERROR(C17/B17,0) -> 1 | E17: =SUMIFS('Historical Data'!$I$4:$I$75,'Historical Data'!$A$4:$A$75,DATE(2025,7,1)) -> 0
A18: Aug | B18: =SUMIFS('Historical Data'!$F$4:$F$75,'Historical Data'!$A$4:$A$75,DATE(2025,8,1)) -> 4169 | C18: =SUMIFS('Historical Data'!$G$4:$G$75,'Historical Data'!$A$4:$A$75,DATE(2025,8,1)) -> 4169 | D18: =IFERROR(C18/B18,0) -> 1 | E18: =SUMIFS('Historical Data'!$I$4:$I$75,'Historical Data'!$A$4:$A$75,DATE(2025,8,1)) -> 0
A19: Sep | B19: =SUMIFS('Historical Data'!$F$4:$F$75,'Historical Data'!$A$4:$A$75,DATE(2025,9,1)) -> 4167 | C19: =SUMIFS('Historical Data'!$G$4:$G$75,'Historical Data'!$A$4:$A$75,DATE(2025,9,1)) -> 4167 | D19: =IFERROR(C19/B19,0) -> 1 | E19: =SUMIFS('Historical Data'!$I$4:$I$75,'Historical Data'!$A$4:$A$75,DATE(2025,9,1)) -> 0
A20: Oct | B20: =SUMIFS('Historical Data'!$F$4:$F$75,'Historical Data'!$A$4:$A$75,DATE(2025,10,1)) -> 4213 | C20: =SUMIFS('Historical Data'!$G$4:$G$75,'Historical Data'!$A$4:$A$75,DATE(2025,10,1)) -> 4213 | D20: =IFERROR(C20/B20,0) -> 1 | E20: =SUMIFS('Historical Data'!$I$4:$I$75,'Historical Data'!$A$4:$A$75,DATE(2025,10,1)) -> 0
A21: Nov | B21: =SUMIFS('Historical Data'!$F$4:$F$75,'Historical Data'!$A$4:$A$75,DATE(2025,11,1)) -> 7366 | C21: =SUMIFS('Historical Data'!$G$4:$G$75,'Historical Data'!$A$4:$A$75,DATE(2025,11,1)) -> 7366 | D21: =IFERROR(C21/B21,0) -> 1 | E21: =SUMIFS('Historical Data'!$I$4:$I$75,'Historical Data'!$A$4:$A$75,DATE(2025,11,1)) -> 0
A22: Dec | B22: =SUMIFS('Historical Data'!$F$4:$F$75,'Historical Data'!$A$4:$A$75,DATE(2025,12,1)) -> 7444 | C22: =SUMIFS('Historical Data'!$G$4:$G$75,'Historical Data'!$A$4:$A$75,DATE(2025,12,1)) -> 7444 | D22: =IFERROR(C22/B22,0) -> 1 | E22: =SUMIFS('Historical Data'!$I$4:$I$75,'Historical Data'!$A$4:$A$75,DATE(2025,12,1)) -> 0
A24: SKU | B24: On Hand | C24: On Order | D24: Reorder Point | E24: Weeks Cover | F24: Alert
A25: ='Inventory Tracker'!A6 -> Original 12oz | B25: ='Inventory Tracker'!B6 -> 1180 | C25: ='Inventory Tracker'!C6 -> 900 | D25: ='Inventory Tracker'!J6 -> 914.88333 | E25: ='Inventory Tracker'!L6 -> 5.521391 | F25: ='Inventory Tracker'!N6 -> GREEN - Sufficient
A26: ='Inventory Tracker'!A7 -> Ginger 12oz | B26: ='Inventory Tracker'!B7 -> 710 | C26: ='Inventory Tracker'!C7 -> 600 | D26: ='Inventory Tracker'!J7 -> 801.8 | E26: ='Inventory Tracker'!L7 -> 4.4346649 | F26: ='Inventory Tracker'!N7 -> GREEN - Sufficient
A27: ='Inventory Tracker'!A8 -> Mango 12oz | B27: ='Inventory Tracker'!B8 -> 520 | C27: ='Inventory Tracker'!C8 -> 800 | D27: ='Inventory Tracker'!J8 -> 796.25 | E27: ='Inventory Tracker'!L8 -> 4.9733124 | F27: ='Inventory Tracker'!N8 -> GREEN - Sufficient
A28: ='Inventory Tracker'!A9 -> Berry 12oz | B28: ='Inventory Tracker'!B9 -> 980 | C28: ='Inventory Tracker'!C9 -> 0 | D28: ='Inventory Tracker'!J9 -> 612.85 | E28: ='Inventory Tracker'!L9 -> 3.8834951 | F28: ='Inventory Tracker'!N9 -> AMBER - Monitor
A29: ='Inventory Tracker'!A10 -> Zero Sugar 12oz | B29: ='Inventory Tracker'!B10 -> 430 | C29: ='Inventory Tracker'!C10 -> 650 | D29: ='Inventory Tracker'!J10 -> 699.96667 | E29: ='Inventory Tracker'!L10 -> 4.8492105 | F29: ='Inventory Tracker'!N10 -> GREEN - Sufficient
A30: ='Inventory Tracker'!A11 -> Variety Pack | B30: ='Inventory Tracker'!B11 -> 650 | C30: ='Inventory Tracker'!C11 -> 900 | D30: ='Inventory Tracker'!J11 -> 855.63333 | E30: ='Inventory Tracker'!L11 -> 4.9169927 | F30: ='Inventory Tracker'!N11 -> GREEN - Sufficient

Sheet Inventory Tracker
A1: Live Inventory & Replenishment Alert Tracker | B1: Live Inventory & Replenishment Alert Tracker | C1: Live Inventory & Replenishment Alert Tracker | D1: Live Inventory & Replenishment Alert Tracker | E1: Live Inventory & Replenishment Alert Tracker | F1: Live Inventory & Replenishment Alert Tracker | G1: Live Inventory & Replenishment Alert Tracker | H1: Live Inventory & Replenishment Alert Tracker | I1: Live Inventory & Replenishment Alert Tracker | J1: Live Inventory & Replenishment Alert Tracker | K1: Live Inventory & Replenishment Alert Tracker | L1: Live Inventory & Replenishment Alert Tracker | M1: Live Inventory & Replenishment Alert Tracker | N1: Live Inventory & Replenishment Alert Tracker | O1: Live Inventory & Replenishment Alert Tracker
A2: Live Inventory & Replenishment Alert Tracker | B2: Live Inventory & Replenishment Alert Tracker | C2: Live Inventory & Replenishment Alert Tracker | D2: Live Inventory & Replenishment Alert Tracker | E2: Live Inventory & Replenishment Alert Tracker | F2: Live Inventory & Replenishment Alert Tracker | G2: Live Inventory & Replenishment Alert Tracker | H2: Live Inventory & Replenishment Alert Tracker | I2: Live Inventory & Replenishment Alert Tracker | J2: Live Inventory & Replenishment Alert Tracker | K2: Live Inventory & Replenishment Alert Tracker | L2: Live Inventory & Replenishment Alert Tracker | M2: Live Inventory & Replenishment Alert Tracker | N2: Live Inventory & Replenishment Alert Tracker | O2: Live Inventory & Replenishment Alert Tracker
A3: Update blue input cells (On Hand, On Order, Lead Time). Formulas and alerts will recalculate automatically. | B3: Update blue input cells (On Hand, On Order, Lead Time). Formulas and alerts will recalculate automatically. | C3: Update blue input cells (On Hand, On Order, Lead Time). Formulas and alerts will recalculate automatically. | D3: Update blue input cells (On Hand, On Order, Lead Time). Formulas and alerts will recalculate automatically. | E3: Update blue input cells (On Hand, On Order, Lead Time). Formulas and alerts will recalculate automatically. | F3: Update blue input cells (On Hand, On Order, Lead Time). Formulas and alerts will recalculate automatically. | G3: Update blue input cells (On Hand, On Order, Lead Time). Formulas and alerts will recalculate automatically. | H3: Update blue input cells (On Hand, On Order, Lead Time). Formulas and alerts will recalculate automatically. | I3: Update blue input cells (On Hand, On Order, Lead Time). Formulas and alerts will recalculate automatically. | J3: Update blue input cells (On Hand, On Order, Lead Time). Formulas and alerts will recalculate automatically. | K3: Update blue input cells (On Hand, On Order, Lead Time). Formulas and alerts will recalculate automatically. | L3: Update blue input cells (On Hand, On Order, Lead Time). Formulas and alerts will recalculate automatically. | M3: Update blue input cells (On Hand, On Order, Lead Time). Formulas and alerts will recalculate automatically. | N3: Update blue input cells (On Hand, On Order, Lead Time). Formulas and alerts will recalculate automatically. | O3: Update blue input cells (On Hand, On Order, Lead Time). Formulas and alerts will recalculate automatically.
A5: SKU | B5: Current On Hand | C5: On Order | D5: Avg Monthly Demand | E5: Peak Multiplier | F5: Peak Forecast | G5: Lead Time (days) | H5: Daily Demand | I5: Safety Stock | J5: Reorder Point | K5: Inventory Position | L5: Weeks of Cover | M5: Recommended Order | N5: Alert | O5: Action
A6: Original 12oz | B6: 1180 | C6: 900 | D6: =AVERAGEIFS('Historical Data'!$F$4:$F$75,'Historical Data'!$B$4:$B$75,A6) -> 1033.5 | E6: =MAX(1,AVERAGEIFS('Historical Data'!$F$4:$F$75,'Historical Data'!$B$4:$B$75,A6,'Historical Data'!$A$4:$A$75,">="&DATE(2025,11,1))/D6) -> 1.5621674 | F6: =D6*E6 -> 1614.5 | G6: 10 | H6: =F6/30 -> 53.816667 | I6: =H6*7 -> 376.71667 | J6: =H6*G6+I6 -> 914.88333 | K6: =B6+C6 -> 2080 | L6: =IFERROR(K6/H6/7,0) -> 5.521391 | M6: =MAX(0,ROUNDUP(F6*1.5-K6,0)) -> 342 | N6: =IF(K6<J6,"RED - Reorder Now",IF(L6<4,"AMBER - Monitor","GREEN - Sufficient")) -> GREEN - Sufficient | O6: =IF(N6="RED - Reorder Now","Place expedited PO",IF(N6="AMBER - Monitor","Review in 48 hours","No action")) -> No action
A7: Ginger 12oz | B7: 710 | C7: 600 | D7: =AVERAGEIFS('Historical Data'!$F$4:$F$75,'Historical Data'!$B$4:$B$75,A7) -> 825.83333 | E7: =MAX(1,AVERAGEIFS('Historical Data'!$F$4:$F$75,'Historical Data'!$B$4:$B$75,A7,'Historical Data'!$A$4:$A$75,">="&DATE(2025,11,1))/D7) -> 1.532997 | F7: =D7*E7 -> 1266 | G7: 12 | H7: =F7/30 -> 42.2 | I7: =H7*7 -> 295.4 | J7: =H7*G7+I7 -> 801.8 | K7: =B7+C7 -> 1310 | L7: =IFERROR(K7/H7/7,0) -> 4.4346649 | M7: =MAX(0,ROUNDUP(F7*1.5-K7,0)) -> 589 | N7: =IF(K7<J7,"RED - Reorder Now",IF(L7<4,"AMBER - Monitor","GREEN - Sufficient")) -> GREEN - Sufficient | O7: =IF(N7="RED - Reorder Now","Place expedited PO",IF(N7="AMBER - Monitor","Review in 48 hours","No action")) -> No action
A8: Mango 12oz | B8: 520 | C8: 800 | D8: =AVERAGEIFS('Historical Data'!$F$4:$F$75,'Historical Data'!$B$4:$B$75,A8) -> 758 | E8: =MAX(1,AVERAGEIFS('Historical Data'!$F$4:$F$75,'Historical Data'!$B$4:$B$75,A8,'Historical Data'!$A$4:$A$75,">="&DATE(2025,11,1))/D8) -> 1.5006596 | F8: =D8*E8 -> 1137.5 | G8: 14 | H8: =F8/30 -> 37.916667 | I8: =H8*7 -> 265.41667 | J8: =H8*G8+I8 -> 796.25 | K8: =B8+C8 -> 1320 | L8: =IFERROR(K8/H8/7,0) -> 4.9733124 | M8: =MAX(0,ROUNDUP(F8*1.5-K8,0)) -> 387 | N8: =IF(K8<J8,"RED - Reorder Now",IF(L8<4,"AMBER - Monitor","GREEN - Sufficient")) -> GREEN - Sufficient | O8: =IF(N8="RED - Reorder Now","Place expedited PO",IF(N8="AMBER - Monitor","Review in 48 hours","No action")) -> No action
A9: Berry 12oz | B9: 980 | C9: 0 | D9: =AVERAGEIFS('Historical Data'!$F$4:$F$75,'Historical Data'!$B$4:$B$75,A9) -> 693.25 | E9: =MAX(1,AVERAGEIFS('Historical Data'!$F$4:$F$75,'Historical Data'!$B$4:$B$75,A9,'Historical Data'!$A$4:$A$75,">="&DATE(2025,11,1))/D9) -> 1.5600433 | F9: =D9*E9 -> 1081.5 | G9: 10 | H9: =F9/30 -> 36.05 | I9: =H9*7 -> 252.35 | J9: =H9*G9+I9 -> 612.85 | K9: =B9+C9 -> 980 | L9: =IFERROR(K9/H9/7,0) -> 3.8834951 | M9: =MAX(0,ROUNDUP(F9*1.5-K9,0)) -> 643 | N9: =IF(K9<J9,"RED - Reorder Now",IF(L9<4,"AMBER - Monitor","GREEN - Sufficient")) -> AMBER - Monitor | O9: =IF(N9="RED - Reorder Now","Place expedited PO",IF(N9="AMBER - Monitor","Review in 48 hours","No action")) -> Review in 48 hours
A10: Zero Sugar 12oz | B10: 430 | C10: 650 | D10: =AVERAGEIFS('Historical Data'!$F$4:$F$75,'Historical Data'!$B$4:$B$75,A10) -> 617.41667 | E10: =MAX(1,AVERAGEIFS('Historical Data'!$F$4:$F$75,'Historical Data'!$B$4:$B$75,A10,'Historical Data'!$A$4:$A$75,">="&DATE(2025,11,1))/D10) -> 1.5459576 | F10: =D10*E10 -> 954.5 | G10: 15 | H10: =F10/30 -> 31.816667 | I10: =H10*7 -> 222.71667 | J10: =H10*G10+I10 -> 699.96667 | K10: =B10+C10 -> 1080 | L10: =IFERROR(K10/H10/7,0) -> 4.8492105 | M10: =MAX(0,ROUNDUP(F10*1.5-K10,0)) -> 352 | N10: =IF(K10<J10,"RED - Reorder Now",IF(L10<4,"AMBER - Monitor","GREEN - Sufficient")) -> GREEN - Sufficient | O10: =IF(N10="RED - Reorder Now","Place expedited PO",IF(N10="AMBER - Monitor","Review in 48 hours","No action")) -> No action
A11: Variety Pack | B11: 650 | C11: 900 | D11: =AVERAGEIFS('Historical Data'!$F$4:$F$75,'Historical Data'!$B$4:$B$75,A11) -> 890.75 | E11: =MAX(1,AVERAGEIFS('Historical Data'!$F$4:$F$75,'Historical Data'!$B$4:$B$75,A11,'Historical Data'!$A$4:$A$75,">="&DATE(2025,11,1))/D11) -> 1.5166994 | F11: =D11*E11 -> 1351 | G11: 12 | H11: =F11/30 -> 45.033333 | I11: =H11*7 -> 315.23333 | J11: =H11*G11+I11 -> 855.63333 | K11: =B11+C11 -> 1550 | L11: =IFERROR(K11/H11/7,0) -> 4.9169927 | M11: =MAX(0,ROUNDUP(F11*1.5-K11,0)) -> 477 | N11: =IF(K11<J11,"RED - Reorder Now",IF(L11<4,"AMBER - Monitor","GREEN - Sufficient")) -> GREEN - Sufficient | O11: =IF(N11="RED - Reorder Now","Place expedited PO",IF(N11="AMBER - Monitor","Review in 48 hours","No action")) -> No action

Sheet Historical Data
A1: Historical Fulfillment Dataset — Synthetic Portfolio Data | B1: Historical Fulfillment Dataset — Synthetic Portfolio Data | C1: Historical Fulfillment Dataset — Synthetic Portfolio Data | D1: Historical Fulfillment Dataset — Synthetic Portfolio Data | E1: Historical Fulfillment Dataset — Synthetic Portfolio Data | F1: Historical Fulfillment Dataset — Synthetic Portfolio Data | G1: Historical Fulfillment Dataset — Synthetic Portfolio Data | H1: Historical Fulfillment Dataset — Synthetic Portfolio Data | I1: Historical Fulfillment Dataset — Synthetic Portfolio Data | J1: Historical Fulfillment Dataset — Synthetic Portfolio Data | K1: Historical Fulfillment Dataset — Synthetic Portfolio Data | L1: Historical Fulfillment Dataset — Synthetic Portfolio Data | M1: Historical Fulfillment Dataset — Synthetic Portfolio Data | N1: Historical Fulfillment Dataset — Synthetic Portfolio Data | O1: Historical Fulfillment Dataset — Synthetic Portfolio Data
A2: Historical Fulfillment Dataset — Synthetic Portfolio Data | B2: Historical Fulfillment Dataset — Synthetic Portfolio Data | C2: Historical Fulfillment Dataset — Synthetic Portfolio Data | D2: Historical Fulfillment Dataset — Synthetic Portfolio Data | E2: Historical Fulfillment Dataset — Synthetic Portfolio Data | F2: Historical Fulfillment Dataset — Synthetic Portfolio Data | G2: Historical Fulfillment Dataset — Synthetic Portfolio Data | H2: Historical Fulfillment Dataset — Synthetic Portfolio Data | I2: Historical Fulfillment Dataset — Synthetic Portfolio Data | J2: Historical Fulfillment Dataset — Synthetic Portfolio Data | K2: Historical Fulfillment Dataset — Synthetic Portfolio Data | L2: Historical Fulfillment Dataset — Synthetic Portfolio Data | M2: Historical Fulfillment Dataset — Synthetic Portfolio Data | N2: Historical Fulfillment Dataset — Synthetic Portfolio Data | O2: Historical Fulfillment Dataset — Synthetic Portfolio Data
A3: Month | B3: SKU | C3: Opening Units | D3: Received Units | E3: Available Units | F3: Demand Units | G3: Shipped Units | H3: Closing Units | I3: Stockout Units | J3: Orders | K3: Orders Fulfilled | L3: Fill Rate | M3: On-Time Deliveries | N3: Forecast Units | O3: Forecast Accuracy
A4: 45658 | B4: Original 12oz | C4: 520 | D4: 241 | E4: =C4+D4 -> 761 | F4: 846 | G4: =MIN(E4,F4) -> 761 | H4: =E4-G4 -> 0 | I4: =MAX(0,F4-G4) -> 85 | J4: 14 | K4: =MAX(0,J4-ROUNDUP(I4/60,0)) -> 12 | L4: =IFERROR(G4/F4,0) -> 0.89952719 | M4: 11 | N4: 694 | O4: =IFERROR(1-ABS(N4-F4)/F4,0) -> 0.82033097
A5: 45658 | B5: Ginger 12oz | C5: 430 | D5: 250 | E5: =C5+D5 -> 680 | F5: 756 | G5: =MIN(E5,F5) -> 680 | H5: =E5-G5 -> 0 | I5: =MAX(0,F5-G5) -> 76 | J5: 13 | K5: =MAX(0,J5-ROUNDUP(I5/60,0)) -> 11 | L5: =IFERROR(G5/F5,0) -> 0.8994709 | M5: 10 | N5: 627 | O5: =IFERROR(1-ABS(N5-F5)/F5,0) -> 0.82936508
A6: 45658 | B6: Mango 12oz | C6: 390 | D6: 222 | E6: =C6+D6 -> 612 | F6: 680 | G6: =MIN(E6,F6) -> 612 | H6: =E6-G6 -> 0 | I6: =MAX(0,F6-G6) -> 68 | J6: 11 | K6: =MAX(0,J6-ROUNDUP(I6/60,0)) -> 9 | L6: =IFERROR(G6/F6,0) -> 0.9 | M6: 8 | N6: 571 | O6: =IFERROR(1-ABS(N6-F6)/F6,0) -> 0.83970588
A7: 45658 | B7: Berry 12oz | C7: 360 | D7: 185 | E7: =C7+D7 -> 545 | F7: 606 | G7: =MIN(E7,F7) -> 545 | H7: =E7-G7 -> 0 | I7: =MAX(0,F7-G7) -> 61 | J7: 10 | K7: =MAX(0,J7-ROUNDUP(I7/60,0)) -> 8 | L7: =IFERROR(G7/F7,0) -> 0.89933993 | M7: 7 | N7: 515 | O7: =IFERROR(1-ABS(N7-F7)/F7,0) -> 0.84983498
A8: 45658 | B8: Zero Sugar 12oz | C8: 330 | D8: 152 | E8: =C8+D8 -> 482 | F8: 535 | G8: =MIN(E8,F8) -> 482 | H8: =E8-G8 -> 0 | I8: =MAX(0,F8-G8) -> 53 | J8: 9 | K8: =MAX(0,J8-ROUNDUP(I8/60,0)) -> 8 | L8: =IFERROR(G8/F8,0) -> 0.90093458 | M8: 7 | N8: 460 | O8: =IFERROR(1-ABS(N8-F8)/F8,0) -> 0.85981308
A9: 45658 | B9: Variety Pack | C9: 450 | D9: 231 | E9: =C9+D9 -> 681 | F9: 757 | G9: =MIN(E9,F9) -> 681 | H9: =E9-G9 -> 0 | I9: =MAX(0,F9-G9) -> 76 | J9: 13 | K9: =MAX(0,J9-ROUNDUP(I9/60,0)) -> 11 | L9: =IFERROR(G9/F9,0) -> 0.8996037 | M9: 10 | N9: 659 | O9: =IFERROR(1-ABS(N9-F9)/F9,0) -> 0.87054161
A10: 45689 | B10: Original 12oz | C10: 0 | D10: 818 | E10: =C10+D10 -> 818 | F10: 909 | G10: =MIN(E10,F10) -> 818 | H10: =E10-G10 -> 0 | I10: =MAX(0,F10-G10) -> 91 | J10: 15 | K10: =MAX(0,J10-ROUNDUP(I10/60,0)) -> 13 | L10: =IFERROR(G10/F10,0) -> 0.89988999 | M10: 11 | N10: 754 | O10: =IFERROR(1-ABS(N10-F10)/F10,0) -> 0.82948295
A11: 45689 | B11: Ginger 12oz | C11: 0 | D11: 642 | E11: =C11+D11 -> 642 | F11: 713 | G11: =MIN(E11,F11) -> 642 | H11: =E11-G11 -> 0 | I11: =MAX(0,F11-G11) -> 71 | J11: 12 | K11: =MAX(0,J11-ROUNDUP(I11/60,0)) -> 10 | L11: =IFERROR(G11/F11,0) -> 0.90042076 | M11: 9 | N11: 599 | O11: =IFERROR(1-ABS(N11-F11)/F11,0) -> 0.8401122
A12: 45689 | B12: Mango 12oz | C12: 0 | D12: 576 | E12: =C12+D12 -> 576 | F12: 640 | G12: =MIN(E12,F12) -> 576 | H12: =E12-G12 -> 0 | I12: =MAX(0,F12-G12) -> 64 | J12: 11 | K12: =MAX(0,J12-ROUNDUP(I12/60,0)) -> 9 | L12: =IFERROR(G12/F12,0) -> 0.9 | M12: 8 | N12: 544 | O12: =IFERROR(1-ABS(N12-F12)/F12,0) -> 0.85
A13: 45689 | B13: Berry 12oz | C13: 0 | D13: 513 | E13: =C13+D13 -> 513 | F13: 570 | G13: =MIN(E13,F13) -> 513 | H13: =E13-G13 -> 0 | I13: =MAX(0,F13-G13) -> 57 | J13: 10 | K13: =MAX(0,J13-ROUNDUP(I13/60,0)) -> 9 | L13: =IFERROR(G13/F13,0) -> 0.9 | M13: 8 | N13: 490 | O13: =IFERROR(1-ABS(N13-F13)/F13,0) -> 0.85964912
A14: 45689 | B14: Zero Sugar 12oz | C14: 0 | D14: 515 | E14: =C14+D14 -> 515 | F14: 572 | G14: =MIN(E14,F14) -> 515 | H14: =E14-G14 -> 0 | I14: =MAX(0,F14-G14) -> 57 | J14: 10 | K14: =MAX(0,J14-ROUNDUP(I14/60,0)) -> 9 | L14: =IFERROR(G14/F14,0) -> 0.90034965 | M14: 8 | N14: 498 | O14: =IFERROR(1-ABS(N14-F14)/F14,0) -> 0.87062937
A15: 45689 | B15: Variety Pack | C15: 0 | D15: 730 | E15: =C15+D15 -> 730 | F15: 811 | G15: =MIN(E15,F15) -> 730 | H15: =E15-G15 -> 0 | I15: =MAX(0,F15-G15) -> 81 | J15: 14 | K15: =MAX(0,J15-ROUNDUP(I15/60,0)) -> 12 | L15: =IFERROR(G15/F15,0) -> 0.9001233 | M15: 11 | N15: 714 | O15: =IFERROR(1-ABS(N15-F15)/F15,0) -> 0.88039457
... A75: 45992 | B75: Variety Pack | C75: 1716 | D75: 1310 | E75: =C75+D75 -> 3026 | F75: 1310 | G75: =MIN(E75,F75) -> 1310 | H75: =E75-G75 -> 1716 | I75: =MAX(0,F75-G75) -> 0 | J75: 22 | K75: =MAX(0,J75-ROUNDUP(I75/60,0)) -> 22 | L75: =IFERROR(G75/F75,0) -> 1 | M75: 21 | N75: 1284 | O75: =IFERROR(1-ABS(N75-F75)/F75,0) -> 0.98015267

Sheet KPI Definitions
A1: KPI Dictionary & Management Rules | B1: KPI Dictionary & Management Rules | C1: KPI Dictionary & Management Rules | D1: KPI Dictionary & Management Rules | E1: KPI Dictionary & Management Rules | F1: KPI Dictionary & Management Rules | G1: KPI Dictionary & Management Rules
A2: KPI Dictionary & Management Rules | B2: KPI Dictionary & Management Rules | C2: KPI Dictionary & Management Rules | D2: KPI Dictionary & Management Rules | E2: KPI Dictionary & Management Rules | F2: KPI Dictionary & Management Rules | G2: KPI Dictionary & Management Rules
A4: KPI | B4: Definition | C4: Formula | D4: Target | E4: Frequency | F4: Owner | G4: Management Use
A5: Order Fill Rate | B5: Share of requested units shipped | C5: Units shipped / Demand units | D5: >= 98% | E5: Weekly | F5: Warehouse PM | G5: Shows ability to satisfy customer demand
A6: Stockout Units | B6: Demand units not shipped | C6: MAX(0, Demand - Shipped) | D6: 0 | E6: Daily | F6: Inventory Lead | G6: Triggers replenishment escalation
A7: Weeks of Cover | B7: Time inventory can support forecast demand | C7: Inventory position / Weekly demand | D7: 4–8 weeks | E7: Weekly | F7: Warehouse PM | G7: Balances availability and excess stock
A8: Reorder Point | B8: Inventory level that triggers replenishment | C8: Lead-time demand + Safety stock | D8: SKU-specific | E8: Weekly | F8: Planner | G8: Prevents depletion before inbound stock arrives
A9: Forecast Accuracy | B9: Closeness of forecast to actual demand | C9: 1 - ABS(Forecast - Actual) / Actual | D9: >= 90% | E9: Monthly | F9: Project Manager | G9: Improves peak-season planning
A10: On-Time Delivery Rate | B10: Fulfilled orders delivered on time | C10: On-time deliveries / Orders fulfilled | D10: >= 95% | E10: Weekly | F10: Delivery Lead | G10: Measures last-mile reliability
A11: Inventory Turnover | B11: Demand consumed relative to average inventory | C11: Annual demand / Average inventory | D11: Monitor trend | E11: Monthly | F11: Operations | G11: Identifies slow or overstocked inventory
A12: Peak Volume Growth | B12: Change in peak shipments vs comparison period | C12: Peak shipped / Baseline shipped - 1 | D12: >= 50% | E12: Seasonal | F12: Project Manager | G12: Demonstrates capacity and sales enablement
A13: Alert Response Time | B13: Time from red alert to action | C13: Action timestamp - Alert timestamp | D13: < 24 hours | E13: Per alert | F13: Project Manager | G13: Measures responsiveness to risk
